kunny/__init__.py
kunny/consumer.py
kunny/provider.py
kunny-0.1.1.dist-info/LICENSE
kunny-0.1.1.dist-info/METADATA
kunny-0.1.1.dist-info/WHEEL
kunny-0.1.1.dist-info/top_level.txt
kunny-0.1.1.dist-info/RECORD
